address_lookup/__init__.py
address_lookup/errors.py
address_lookup/result.py
address_lookup/clients/__init__.py
address_lookup/clients/client.py
address_lookup/clients/here_client.py
address_lookup-0.0.6.dist-info/LICENSE
address_lookup-0.0.6.dist-info/METADATA
address_lookup-0.0.6.dist-info/WHEEL
address_lookup-0.0.6.dist-info/top_level.txt
address_lookup-0.0.6.dist-info/RECORD
