Metadata-Version: 2.1
Name: address-lookup
Version: 0.0.6
Summary: Lookup an address using an online provider
Home-page: https://github.com/rstular/address-lookup
Author: rstular
Author-email: dev@rstular.eu
License: UNKNOWN
Project-URL: Bug Tracker, https://github.com/rstular/address-lookup/issues
Platform: UNKNOWN
Classifier: Programming Language :: Python :: 3
Classifier: Programming Language :: Python :: 3.6
Classifier: Programming Language :: Python :: 3.7
Classifier: Programming Language :: Python :: 3.8
Classifier: Programming Language :: Python :: 3.9
Classifier: Programming Language :: Python :: 3.10
Classifier: Programming Language :: Python :: 3.11
Classifier: Topic :: Office/Business
Classifier: License :: OSI Approved :: MIT License
Classifier: Operating System :: OS Independent
Requires-Python: >=3.6
License-File: LICENSE
Requires-Dist: requests
